unknown_terms/__init__.py
unknown_terms/alpha_term.py
unknown_terms/multiple_alpha_term.py
unknown_terms/printer.py
unknown_terms-1.0.2.dist-info/LICENSE
unknown_terms-1.0.2.dist-info/METADATA
unknown_terms-1.0.2.dist-info/WHEEL
unknown_terms-1.0.2.dist-info/top_level.txt
unknown_terms-1.0.2.dist-info/RECORD
