Metadata-Version: 2.1
Name: unknown-terms
Version: 1.0.2
Summary: Unknown terms library for math apps
Author-email: "@lightningcell (Hamit Şimşek)" <hamidsimsek4457@gmail.com>
License: MIT License
Project-URL: Homepage, https://github.com/lightningcell/unknown-terms
Keywords: python,math,binom,derrivative,integral
Classifier: License :: OSI Approved :: MIT License
Classifier: Programming Language :: Python
Classifier: Programming Language :: Python :: 3
Requires-Python: >=3.8
License-File: LICENSE
Provides-Extra: dev
Requires-Dist: black ; extra == 'dev'
Requires-Dist: bumpver ; extra == 'dev'
Requires-Dist: isort ; extra == 'dev'
Requires-Dist: pip-tools ; extra == 'dev'
Requires-Dist: pytest ; extra == 'dev'
